sortpixels/__init__.py
sortpixels/sortimage.py
sortpixels/test/__init__.py
sortpixels/test/test_sortimage.py
sortpixels-0.1.3.data/scripts/example.py
sortpixels-0.1.3.dist-info/LICENSE.txt
sortpixels-0.1.3.dist-info/METADATA
sortpixels-0.1.3.dist-info/WHEEL
sortpixels-0.1.3.dist-info/top_level.txt
sortpixels-0.1.3.dist-info/RECORD
