Metadata-Version: 2.1
Name: sortpixels
Version: 0.1.3
Summary: Useful image sorter.
Author: Matthew Edelen
License: LICENSE.txt
Platform: UNKNOWN
License-File: LICENSE.txt
Requires-Dist: Pillow (>=9.0)
Requires-Dist: numpy (>=1.22)
